{
  "cli": {
    "version": ">= 13.2.0",
    "appVersionSource": "local"
  },
  "build": {
    "development": {
      "developmentClient": true,
      "distribution": "internal",
      "node": "20.18.0",
      "ios": {
        "simulator": false,
        "buildConfiguration": "Release",
        "resourceClass": "m-medium"
      },
      "android": {
        "buildType": "apk",
        "gradleCommand": ":app:assembleDebug"
      }
    },
    "preview": {
      "distribution": "internal",
      "node": "20.18.0",
      "env": {
        "NPM_CONFIG_LEGACY_PEER_DEPS": "true"
      },
      "ios": {
        "simulator": false
      },
      "android": {
        "buildType": "apk",
        "gradleCommand": ":app:assembleRelease"
      }
    },
    "production": {
      "ios": {
        "simulator": false
      },
      "android": {
        "buildType": "app-bundle",
        "buildConfiguration": "Release"
      }
    },
    "preview-small": {
      "extends": "preview",
      "android": {
        "buildType": "app-bundle",
        "gradleCommand": ":app:bundleRelease"
      }
    }
  },
  "submit": {
    "production": {}
  }
}
